importlib_metadata_argparse_version/__init__.py
importlib_metadata_argparse_version-3.0.0.dist-info/METADATA
importlib_metadata_argparse_version-3.0.0.dist-info/WHEEL
importlib_metadata_argparse_version-3.0.0.dist-info/licenses/LICENSE
importlib_metadata_argparse_version-3.0.0.dist-info/RECORD
