Metadata-Version: 2.3
Name: importlib-metadata-argparse-version
Version: 3.0.0
Summary: Argparse action to define CLI version with a delayed call to importlib.metadata
Project-URL: Source, https://github.com/mondeja/importlib-metadata-argparse-version
Project-URL: Documentation, https://github.com/mondeja/importlib-metadata-argparse-version?tab=readme-ov-file#usage
Project-URL: Bug tracker, https://github.com/mondeja/importlib-metadata-argparse-version/issues
Project-URL: Changelog, https://github.com/mondeja/importlib-metadata-argparse-version/releases
Author-email: Álvaro Mondéjar Rubio <mondejar1994@gmail.com>
License-Expression: BSD-3-Clause
License-File: LICENSE
Keywords: argparse,cli,importlib,metadata,performance,version
Classifier: Development Status :: 5 - Production/Stable
Classifier: Intended Audience :: Developers
Classifier: License :: OSI Approved :: BSD License
Classifier: Operating System :: OS Independent
Classifier: Programming Language :: Python
Classifier: Programming Language :: Python :: 3 :: Only
Classifier: Programming Language :: Python :: 3.9
Classifier: Programming Language :: Python :: 3.10
Classifier: Programming Language :: Python :: 3.11
Classifier: Programming Language :: Python :: 3.12
Classifier: Programming Language :: Python :: 3.13
Classifier: Topic :: Software Development :: Libraries
Requires-Python: >=3.9
